generic_links/__init__.py
generic_links/admin.py
generic_links/apps.py
generic_links/forms.py
generic_links/managers.py
generic_links/models.py
generic_links/urls.py
generic_links/utils.py
generic_links/views.py
generic_links/migrations/0001_initial.py
generic_links/migrations/0002_alter_genericlink_id_and_more.py
generic_links/migrations/__init__.py
generic_links/static/css/generic_links.css
generic_links/static/img/.gitignore
generic_links/static/js/generic_links.js
generic_links/templates/generic_links/add.html
generic_links/templates/generic_links/base.html
generic_links/templatetags/__init__.py
generic_links/templatetags/generic_links_tags.py
django_generic_links-0.13.0.dist-info/METADATA
django_generic_links-0.13.0.dist-info/WHEEL
django_generic_links-0.13.0.dist-info/licenses/AUTHORS.md
django_generic_links-0.13.0.dist-info/licenses/LICENSE
django_generic_links-0.13.0.dist-info/RECORD
