Metadata-Version: 2.4
Name: django-generic-links
Version: 0.13.0
Summary: Simple and generic application for Django projects to attach and handle links for any object
Project-URL: Homepage, https://matagus.github.io/django-generic-links/
Project-URL: Issues, https://github.com/matagus/django-generic-links/issues
Project-URL: Repository, https://github.com/matagus/django-generic-links
Project-URL: Changelog, https://github.com/matagus/django-generic-links/releases
Project-URL: Pypi, https://pypi.org/project/django-generic-links
Author-email: Matias Agustin Mendez <matagus@gmail.com>
License-Expression: BSD-3-Clause
License-File: AUTHORS.md
License-File: LICENSE
Keywords: django,generic app,generic links,links,urls
Classifier: Development Status :: 5 - Production/Stable
Classifier: Environment :: Console
Classifier: Environment :: Web Environment
Classifier: Framework :: Django
Classifier: Framework :: Django :: 4.2
Classifier: Framework :: Django :: 5.0
Classifier: Framework :: Django :: 5.1
Classifier: Framework :: Django :: 5.2
Classifier: Framework :: Django :: 6.0
Classifier: Intended Audience :: Developers
Classifier: License :: OSI Approved :: BSD License
Classifier: Natural Language :: English
Classifier: Programming Language :: Python
Classifier: Programming Language :: Python :: 3.12
Classifier: Programming Language :: Python :: 3.13
Classifier: Programming Language :: Python :: 3.14
Classifier: Programming Language :: Python :: Implementation :: CPython
Classifier: Programming Language :: Python :: Implementation :: PyPy
Classifier: Topic :: Software Development :: Libraries
Requires-Dist: django>=4.2
Provides-Extra: docs
Requires-Dist: mkdocs; extra == 'docs'
Requires-Dist: mkdocs-material; extra == 'docs'
Requires-Dist: pygments; extra == 'docs'
Requires-Dist: pymdown-extensions; extra == 'docs'
